fx_bin/__init__.py
fx_bin/backup.py
fx_bin/backup_utils.py
fx_bin/cli.py
fx_bin/common.py
fx_bin/common_functional.py
fx_bin/errors.py
fx_bin/files.py
fx_bin/filter.py
fx_bin/find_files.py
fx_bin/lib.py
fx_bin/organize.py
fx_bin/organize_functional.py
fx_bin/py_fx_bin.py
fx_bin/realpath.py
fx_bin/replace.py
fx_bin/replace_functional.py
fx_bin/root.py
fx_bin/shared_types.py
fx_bin/size.py
fx_bin/today.py
fx_bin-2.6.0.dist-info/METADATA
fx_bin-2.6.0.dist-info/WHEEL
fx_bin-2.6.0.dist-info/entry_points.txt
fx_bin-2.6.0.dist-info/RECORD
