Metadata-Version: 2.4
Name: fx-bin
Version: 2.6.0
Summary: A common bin collection for my own usage
Keywords: fx_bin
Author: Frank Xu
Author-email: frank@frankxu.me
Requires-Python: >=3.11,<4.0
Classifier: Intended Audience :: Developers
Classifier: Programming Language :: Python :: 3
Classifier: Programming Language :: Python :: 3.11
Classifier: Programming Language :: Python :: 3.12
Classifier: Programming Language :: Python :: 3.13
Classifier: Programming Language :: Python :: 3.14
Requires-Dist: click (>=8.1.3,<9.0.0)
Requires-Dist: loguru (>=0.7.0,<0.8.0)
Requires-Dist: returns (>=0.22.0,<0.23.0)
Project-URL: Repository, https://github.com/frankyxhl/fx_bin
